osvg/__init__.py
osvg/float.py
osvg/float_math.py
osvg/helper.py
osvg/positions.py
osvg/style.py
osvg/elements/circle.py
osvg/elements/circlebase.py
osvg/elements/elementbase.py
osvg/elements/ellipse.py
osvg/elements/group.py
osvg/elements/line.py
osvg/elements/line_marker.py
osvg/elements/path.py
osvg/elements/polyline.py
osvg/elements/rectangle.py
osvg/elements/rectanglebase.py
osvg/elements/svg.py
osvg/elements/text.py
osvg-2.1.1.dist-info/METADATA
osvg-2.1.1.dist-info/WHEEL
osvg-2.1.1.dist-info/licenses/LICENSE
osvg-2.1.1.dist-info/RECORD
