Metadata-Version: 2.3
Name: osvg
Version: 2.1.1
Summary: osvg is a python API to create SVG XML code with object-oriented elements
Project-URL: Homepage, https://gitlab.com/ko.no/osvg
Project-URL: Bug Tracker, https://gitlab.com/ko.no/osvg/-/issues
Author-email: Korte Noack <korte@8lacht.de>
License-File: LICENSE
Classifier: Development Status :: 5 - Production/Stable
Classifier: Intended Audience :: Developers
Classifier: License :: OSI Approved :: GNU General Public License v3 (GPLv3)
Classifier: Operating System :: OS Independent
Classifier: Programming Language :: Python :: 3.10
Classifier: Programming Language :: Python :: 3.11
Classifier: Programming Language :: Python :: 3.12
Requires-Python: >=3.10
Requires-Dist: typing-extensions
